{
  "examId": "common_retake/2026/english",
  "submissionId": "demo-10000002-common_retake-2026-english-01",
  "score": 82,
  "maxScore": 100,
  "feedback": "Demo marksheet graded result generated from question-level answers.",
  "gradedAt": "2026-06-01T08:18:00.000Z",
  "sections": [
    {
      "id": "s1",
      "title": "第1問",
      "score": 6,
      "maxScore": 6,
      "feedback": "Answer pattern is stable.",
      "retryRecommended": false
    },
    {
      "id": "s2",
      "title": "第2問",
      "score": 12,
      "maxScore": 12,
      "feedback": "Answer pattern is stable.",
      "retryRecommended": false
    },
    {
      "id": "s3",
      "title": "第3問",
      "score": 6,
      "maxScore": 10,
      "feedback": "Answer pattern is stable.",
      "retryRecommended": false
    },
    {
      "id": "s4",
      "title": "第4問",
      "score": 12,
      "maxScore": 12,
      "feedback": "Answer pattern is stable.",
      "retryRecommended": false
    },
    {
      "id": "s5",
      "title": "第5問",
      "score": 12,
      "maxScore": 16,
      "feedback": "Answer pattern is stable.",
      "retryRecommended": false
    },
    {
      "id": "s6",
      "title": "第6問",
      "score": 9,
      "maxScore": 13,
      "feedback": "Answer pattern is stable.",
      "retryRecommended": false
    },
    {
      "id": "s7",
      "title": "第7問",
      "score": 16,
      "maxScore": 16,
      "feedback": "Answer pattern is stable.",
      "retryRecommended": false
    },
    {
      "id": "s8",
      "title": "第8問",
      "score": 9,
      "maxScore": 15,
      "feedback": "Answer pattern is stable.",
      "retryRecommended": false
    }
  ]
}
