[
  {
    "id": "10000001-1275550111",
    "studentId": "10000001",
    "admissionCode": "1275550111",
    "university": "東京大学",
    "faculty": "理科一類",
    "department": "",
    "method": "",
    "schedule": "前期",
    "bRate": 89.5,
    "createdAt": "2026-04-12T10:28:57.830Z"
  },
  {
    "id": "10000011-demo-goal",
    "studentId": "10000011",
    "admissionCode": "demo-10000011",
    "university": "早稲田大学",
    "faculty": "文化構想学部",
    "department": "",
    "method": "",
    "schedule": "",
    "bRate": 78,
    "createdAt": "2026-04-13T00:00:00.000Z"
  },
  {
    "id": "10000012-demo-goal",
    "studentId": "10000012",
    "admissionCode": "demo-10000012",
    "university": "慶應義塾大学",
    "faculty": "商学部",
    "department": "",
    "method": "",
    "schedule": "",
    "bRate": 80,
    "createdAt": "2026-04-13T00:00:00.000Z"
  },
  {
    "id": "10000013-demo-goal",
    "studentId": "10000013",
    "admissionCode": "demo-10000013",
    "university": "東京大学",
    "faculty": "文科三類",
    "department": "",
    "method": "",
    "schedule": "",
    "bRate": 87,
    "createdAt": "2026-04-13T00:00:00.000Z"
  },
  {
    "id": "10000014-demo-goal",
    "studentId": "10000014",
    "admissionCode": "demo-10000014",
    "university": "一橋大学",
    "faculty": "商学部",
    "department": "",
    "method": "",
    "schedule": "",
    "bRate": 84,
    "createdAt": "2026-04-13T00:00:00.000Z"
  },
  {
    "id": "10000015-demo-goal",
    "studentId": "10000015",
    "admissionCode": "demo-10000015",
    "university": "明治大学",
    "faculty": "法学部",
    "department": "",
    "method": "",
    "schedule": "",
    "bRate": 74,
    "createdAt": "2026-04-13T00:00:00.000Z"
  },
  {
    "id": "10000017-demo-goal",
    "studentId": "10000017",
    "admissionCode": "demo-10000017",
    "university": "青山学院大学",
    "faculty": "教育人間科学部",
    "department": "",
    "method": "",
    "schedule": "",
    "bRate": 71,
    "createdAt": "2026-04-13T00:00:00.000Z"
  },
  {
    "id": "10000019-demo-goal",
    "studentId": "10000019",
    "admissionCode": "demo-10000019",
    "university": "中央大学",
    "faculty": "国際情報学部",
    "department": "",
    "method": "",
    "schedule": "",
    "bRate": 73,
    "createdAt": "2026-04-13T00:00:00.000Z"
  },
  {
    "id": "10000020-demo-goal",
    "studentId": "10000020",
    "admissionCode": "demo-10000020",
    "university": "法政大学",
    "faculty": "経営学部",
    "department": "",
    "method": "",
    "schedule": "",
    "bRate": 70,
    "createdAt": "2026-04-13T00:00:00.000Z"
  },
  {
    "id": "41989359-3549470572",
    "studentId": "41989359",
    "admissionCode": "3549470572",
    "university": "名城大",
    "faculty": "理工",
    "department": "電気電子工",
    "method": "前期３",
    "schedule": "共",
    "bRate": 73.8,
    "createdAt": "2026-04-19T09:14:25.097Z"
  },
  {
    "id": "88733246-2150550310",
    "studentId": "88733246",
    "admissionCode": "2150550310",
    "university": "名古屋市立大",
    "faculty": "医",
    "department": "保健／理学療",
    "method": "",
    "schedule": "前",
    "bRate": 65.9,
    "createdAt": "2026-04-19T09:14:25.105Z"
  },
  {
    "id": "36310748-1275461810",
    "studentId": "36310748",
    "admissionCode": "1275461810",
    "university": "名古屋大",
    "faculty": "工",
    "department": "機械・航空宇",
    "method": "",
    "schedule": "前",
    "bRate": 81.1,
    "createdAt": "2026-04-19T09:14:25.113Z"
  },
  {
    "id": "65414529-2150610250",
    "studentId": "65414529",
    "admissionCode": "2150610250",
    "university": "名古屋市立大",
    "faculty": "薬",
    "department": "薬",
    "method": "",
    "schedule": "中",
    "bRate": 82.9,
    "createdAt": "2026-04-19T09:14:25.121Z"
  },
  {
    "id": "93434291-2135030210",
    "studentId": "93434291",
    "admissionCode": "2135030210",
    "university": "愛知県立大",
    "faculty": "日本文化",
    "department": "歴史文化",
    "method": "",
    "schedule": "前",
    "bRate": 69,
    "createdAt": "2026-04-19T09:14:25.129Z"
  },
  {
    "id": "11078131-1275461310",
    "studentId": "11078131",
    "admissionCode": "1275461310",
    "university": "名古屋大",
    "faculty": "工",
    "department": "物理工",
    "method": "",
    "schedule": "前",
    "bRate": 77.2,
    "createdAt": "2026-04-19T09:14:25.135Z"
  },
  {
    "id": "61422064-3349370173",
    "studentId": "61422064",
    "admissionCode": "3349370173",
    "university": "東京情報デ職大",
    "faculty": "情報デザ",
    "department": "情報デザイン",
    "method": "前期Ⅱ",
    "schedule": "共",
    "bRate": 45,
    "createdAt": "2026-04-19T09:14:25.142Z"
  },
  {
    "id": "65301797-1275420010",
    "studentId": "65301797",
    "admissionCode": "1275420010",
    "university": "名古屋大",
    "faculty": "理",
    "department": "",
    "method": "",
    "schedule": "前",
    "bRate": 78.9,
    "createdAt": "2026-04-19T09:14:25.148Z"
  },
  {
    "id": "95138218-1250461210",
    "studentId": "95138218",
    "admissionCode": "1250461210",
    "university": "岐阜大",
    "faculty": "工",
    "department": "機械／機械",
    "method": "",
    "schedule": "前",
    "bRate": 65,
    "createdAt": "2026-04-19T09:14:25.155Z"
  },
  {
    "id": "11369964-2135080110",
    "studentId": "11369964",
    "admissionCode": "2135080110",
    "university": "愛知県立大",
    "faculty": "外国語",
    "department": "英米",
    "method": "",
    "schedule": "前",
    "bRate": 70,
    "createdAt": "2026-04-19T09:14:25.162Z"
  },
  {
    "id": "63104218-1275720410",
    "studentId": "63104218",
    "admissionCode": "1275720410",
    "university": "名古屋大",
    "faculty": "農",
    "department": "資源生物科学",
    "method": "",
    "schedule": "前",
    "bRate": 77.4,
    "createdAt": "2026-04-19T09:14:25.169Z"
  },
  {
    "id": "29062271-1275461810",
    "studentId": "29062271",
    "admissionCode": "1275461810",
    "university": "名古屋大",
    "faculty": "工",
    "department": "機械・航空宇",
    "method": "",
    "schedule": "前",
    "bRate": 81.1,
    "createdAt": "2026-04-19T09:14:25.176Z"
  },
  {
    "id": "19640196-2135030110",
    "studentId": "19640196",
    "admissionCode": "2135030110",
    "university": "愛知県立大",
    "faculty": "日本文化",
    "department": "国語国文",
    "method": "",
    "schedule": "前",
    "bRate": 71,
    "createdAt": "2026-04-19T09:14:25.184Z"
  },
  {
    "id": "11685791-3546080276",
    "studentId": "11685791",
    "admissionCode": "3546080276",
    "university": "南山大",
    "faculty": "外国語",
    "department": "英米",
    "method": "併用文",
    "schedule": "共",
    "bRate": 84,
    "createdAt": "2026-04-19T09:14:25.190Z"
  },
  {
    "id": "66947532-3549471571",
    "studentId": "66947532",
    "admissionCode": "3549471571",
    "university": "名城大",
    "faculty": "理工",
    "department": "メカトロニク",
    "method": "前期３",
    "schedule": "共",
    "bRate": 72.5,
    "createdAt": "2026-04-19T09:14:25.197Z"
  },
  {
    "id": "19316238-1125462610",
    "studentId": "19316238",
    "admissionCode": "1125462610",
    "university": "千葉大",
    "faculty": "工",
    "department": "総合／デザイ",
    "method": "",
    "schedule": "前",
    "bRate": 74.7,
    "createdAt": "2026-04-19T09:14:25.203Z"
  },
  {
    "id": "48190813-1265301210",
    "studentId": "48190813",
    "admissionCode": "1265301210",
    "university": "愛知教育大",
    "faculty": "教育",
    "department": "学校／高英語",
    "method": "",
    "schedule": "前",
    "bRate": 67.9,
    "createdAt": "2026-04-19T09:14:25.210Z"
  },
  {
    "id": "12462877-1280461810",
    "studentId": "12462877",
    "admissionCode": "1280461810",
    "university": "名古屋工大",
    "faculty": "工",
    "department": "電気・機械工",
    "method": "",
    "schedule": "前",
    "bRate": 73.3,
    "createdAt": "2026-04-19T09:14:25.218Z"
  },
  {
    "id": "91839272-1265301110",
    "studentId": "91839272",
    "admissionCode": "1265301110",
    "university": "愛知教育大",
    "faculty": "教育",
    "department": "学校／高理科",
    "method": "",
    "schedule": "前",
    "bRate": 67.4,
    "createdAt": "2026-04-19T09:14:25.225Z"
  },
  {
    "id": "24806266-3521190175",
    "studentId": "24806266",
    "admissionCode": "3521190175",
    "university": "愛知大",
    "faculty": "経営",
    "department": "経営",
    "method": "併用",
    "schedule": "共",
    "bRate": 75,
    "createdAt": "2026-04-19T09:14:25.232Z"
  },
  {
    "id": "89702052-1250740510",
    "studentId": "89702052",
    "admissionCode": "1250740510",
    "university": "岐阜大",
    "faculty": "応用生物",
    "department": "応用生命化",
    "method": "",
    "schedule": "前",
    "bRate": 72,
    "createdAt": "2026-04-19T09:14:25.239Z"
  },
  {
    "id": "50397737-1280461310",
    "studentId": "50397737",
    "admissionCode": "1280461310",
    "university": "名古屋工大",
    "faculty": "工",
    "department": "情報工",
    "method": "",
    "schedule": "前",
    "bRate": 74.4,
    "createdAt": "2026-04-19T09:14:25.246Z"
  },
  {
    "id": "89449095-2135640110",
    "studentId": "89449095",
    "admissionCode": "2135640110",
    "university": "愛知県立大",
    "faculty": "看護",
    "department": "看護",
    "method": "",
    "schedule": "前",
    "bRate": 62.3,
    "createdAt": "2026-04-19T09:14:25.253Z"
  },
  {
    "id": "18153077-1275461310",
    "studentId": "18153077",
    "admissionCode": "1275461310",
    "university": "名古屋大",
    "faculty": "工",
    "department": "物理工",
    "method": "",
    "schedule": "前",
    "bRate": 77.2,
    "createdAt": "2026-04-19T09:14:25.260Z"
  },
  {
    "id": "69584603-1275461810",
    "studentId": "69584603",
    "admissionCode": "1275461810",
    "university": "名古屋大",
    "faculty": "工",
    "department": "機械・航空宇",
    "method": "",
    "schedule": "前",
    "bRate": 81.1,
    "createdAt": "2026-04-19T09:14:25.267Z"
  },
  {
    "id": "67785888-2135030210",
    "studentId": "67785888",
    "admissionCode": "2135030210",
    "university": "愛知県立大",
    "faculty": "日本文化",
    "department": "歴史文化",
    "method": "",
    "schedule": "前",
    "bRate": 69,
    "createdAt": "2026-04-19T09:14:25.275Z"
  },
  {
    "id": "67233628-1190370210",
    "studentId": "67233628",
    "admissionCode": "1190370210",
    "university": "横浜国立大",
    "faculty": "都市科学",
    "department": "建築",
    "method": "",
    "schedule": "前",
    "bRate": 83,
    "createdAt": "2026-04-19T09:14:25.283Z"
  },
  {
    "id": "89857489-1275461410",
    "studentId": "89857489",
    "admissionCode": "1275461410",
    "university": "名古屋大",
    "faculty": "工",
    "department": "環境土木・建",
    "method": "",
    "schedule": "前",
    "bRate": 78,
    "createdAt": "2026-04-19T09:14:25.290Z"
  },
  {
    "id": "25394409-1280461810",
    "studentId": "25394409",
    "admissionCode": "1280461810",
    "university": "名古屋工大",
    "faculty": "工",
    "department": "電気・機械工",
    "method": "",
    "schedule": "前",
    "bRate": 73.3,
    "createdAt": "2026-04-19T09:14:25.297Z"
  },
  {
    "id": "50251912-1250740410",
    "studentId": "50251912",
    "admissionCode": "1250740410",
    "university": "岐阜大",
    "faculty": "応用生物",
    "department": "共同獣医",
    "method": "",
    "schedule": "前",
    "bRate": 81.1,
    "createdAt": "2026-04-19T09:14:25.304Z"
  },
  {
    "id": "31470320-1265301110",
    "studentId": "31470320",
    "admissionCode": "1265301110",
    "university": "愛知教育大",
    "faculty": "教育",
    "department": "学校／高理科",
    "method": "",
    "schedule": "前",
    "bRate": 67.4,
    "createdAt": "2026-04-19T09:14:25.312Z"
  },
  {
    "id": "54960820-2150270410",
    "studentId": "54960820",
    "admissionCode": "2150270410",
    "university": "名古屋市立大",
    "faculty": "人文社会",
    "department": "心理／教育学",
    "method": "",
    "schedule": "前",
    "bRate": 74.4,
    "createdAt": "2026-04-19T09:14:25.320Z"
  },
  {
    "id": "61194032-1280461610",
    "studentId": "61194032",
    "admissionCode": "1280461610",
    "university": "名古屋工大",
    "faculty": "工",
    "department": "生命・応用化",
    "method": "",
    "schedule": "前",
    "bRate": 70,
    "createdAt": "2026-04-19T09:14:25.327Z"
  },
  {
    "id": "67993582-1210610110",
    "studentId": "67993582",
    "admissionCode": "1210610110",
    "university": "富山大",
    "faculty": "薬",
    "department": "薬",
    "method": "",
    "schedule": "前",
    "bRate": 77.5,
    "createdAt": "2026-04-19T09:14:25.333Z"
  },
  {
    "id": "34315799-2150550310",
    "studentId": "34315799",
    "admissionCode": "2150550310",
    "university": "名古屋市立大",
    "faculty": "医",
    "department": "保健／理学療",
    "method": "",
    "schedule": "前",
    "bRate": 65.9,
    "createdAt": "2026-04-19T09:14:25.341Z"
  },
  {
    "id": "78831853-3608472177",
    "studentId": "78831853",
    "admissionCode": "3608472177",
    "university": "立命館大",
    "faculty": "理工",
    "department": "物理科学",
    "method": "５教科",
    "schedule": "共",
    "bRate": 78.6,
    "createdAt": "2026-04-19T09:14:25.348Z"
  },
  {
    "id": "42311807-1070610010",
    "studentId": "42311807",
    "admissionCode": "1070610010",
    "university": "東北大",
    "faculty": "薬",
    "department": "",
    "method": "",
    "schedule": "前",
    "bRate": 78.9,
    "createdAt": "2026-04-19T09:14:25.355Z"
  },
  {
    "id": "18646072-1280461810",
    "studentId": "18646072",
    "admissionCode": "1280461810",
    "university": "名古屋工大",
    "faculty": "工",
    "department": "電気・機械工",
    "method": "",
    "schedule": "前",
    "bRate": 73.3,
    "createdAt": "2026-04-19T09:14:25.363Z"
  },
  {
    "id": "40404235-1280462310",
    "studentId": "40404235",
    "admissionCode": "1280462310",
    "university": "名古屋工大",
    "faculty": "工",
    "department": "創造／材料エ",
    "method": "",
    "schedule": "前",
    "bRate": 68.9,
    "createdAt": "2026-04-19T09:14:25.370Z"
  },
  {
    "id": "46838890-1280461810",
    "studentId": "46838890",
    "admissionCode": "1280461810",
    "university": "名古屋工大",
    "faculty": "工",
    "department": "電気・機械工",
    "method": "",
    "schedule": "前",
    "bRate": 73.3,
    "createdAt": "2026-04-19T09:14:25.378Z"
  },
  {
    "id": "94887869-2150180310",
    "studentId": "94887869",
    "admissionCode": "2150180310",
    "university": "名古屋市立大",
    "faculty": "経済",
    "department": "経済経営",
    "method": "",
    "schedule": "前",
    "bRate": 75,
    "createdAt": "2026-04-19T09:14:25.385Z"
  },
  {
    "id": "10000002-demo-goal",
    "studentId": "10000002",
    "admissionCode": "demo-10000002",
    "university": "東京大学",
    "faculty": "理科一類",
    "department": "",
    "method": "前期日程",
    "schedule": "前期",
    "bRate": 89.5,
    "createdAt": "2026-04-12T10:28:57.830Z"
  },
  {
    "id": "10000003-demo-goal",
    "studentId": "10000003",
    "admissionCode": "demo-10000003",
    "university": "名古屋大学",
    "faculty": "工学部",
    "department": "機械・航空宇宙工学科",
    "method": "前期日程",
    "schedule": "前期",
    "bRate": 82,
    "createdAt": "2026-04-12T10:28:57.830Z"
  },
  {
    "id": "10000004-demo-goal",
    "studentId": "10000004",
    "admissionCode": "demo-10000004",
    "university": "京都大学",
    "faculty": "経済学部",
    "department": "経済経営学科",
    "method": "前期日程",
    "schedule": "前期",
    "bRate": 83,
    "createdAt": "2026-04-12T10:28:57.830Z"
  },
  {
    "id": "10000005-demo-goal",
    "studentId": "10000005",
    "admissionCode": "demo-10000005",
    "university": "浜松医科大学",
    "faculty": "医学部",
    "department": "医学科",
    "method": "前期日程",
    "schedule": "前期",
    "bRate": 80,
    "createdAt": "2026-04-12T10:28:57.830Z"
  },
  {
    "id": "10000006-demo-goal",
    "studentId": "10000006",
    "admissionCode": "demo-10000006",
    "university": "静岡大学",
    "faculty": "人文社会科学部",
    "department": "法学科",
    "method": "前期日程",
    "schedule": "前期",
    "bRate": 72,
    "createdAt": "2026-04-12T10:28:57.830Z"
  },
  {
    "id": "10000007-demo-goal",
    "studentId": "10000007",
    "admissionCode": "demo-10000007",
    "university": "名古屋大学",
    "faculty": "工学部",
    "department": "機械・航空宇宙工学科",
    "method": "前期日程",
    "schedule": "前期",
    "bRate": 80,
    "createdAt": "2026-05-18T00:00:00.000Z"
  }
]
